OgcBiaozhunguifan/README.md
OgcBiaozhunguifan/__init__.py
OgcBiaozhunguifan/__main__.py
OgcBiaozhunguifan/file.epub
OgcBiaozhunguifan/index.html
OgcBiaozhunguifan/css/__init__.py
OgcBiaozhunguifan/css/annotations.css
OgcBiaozhunguifan/css/main.css
OgcBiaozhunguifan/css/normalize.css
OgcBiaozhunguifan/css/popup.css
OgcBiaozhunguifan/font/__init__.py
OgcBiaozhunguifan/font/fontello.eot
OgcBiaozhunguifan/font/fontello.svg
OgcBiaozhunguifan/font/fontello.ttf
OgcBiaozhunguifan/font/fontello.woff
OgcBiaozhunguifan/img/__init__.py
OgcBiaozhunguifan/img/annotator-glyph-sprite.png
OgcBiaozhunguifan/img/annotator-icon-sprite.png
OgcBiaozhunguifan/img/apple-touch-icon.png
OgcBiaozhunguifan/img/cancelfullscreen.png
OgcBiaozhunguifan/img/close.png
OgcBiaozhunguifan/img/fullscreen.png
OgcBiaozhunguifan/img/loader.gif
OgcBiaozhunguifan/img/menu-icon.png
OgcBiaozhunguifan/img/save.png
OgcBiaozhunguifan/img/saved.png
OgcBiaozhunguifan/img/settings-s.png
OgcBiaozhunguifan/img/settings.png
OgcBiaozhunguifan/img/star.png
OgcBiaozhunguifan/js/__init__.py
OgcBiaozhunguifan/js/epub.js
OgcBiaozhunguifan/js/epub.min.js
OgcBiaozhunguifan/js/epub.min.map
OgcBiaozhunguifan/js/hooks.min.js
OgcBiaozhunguifan/js/hooks.min.map
OgcBiaozhunguifan/js/reader.js
OgcBiaozhunguifan/js/reader.js.map
OgcBiaozhunguifan/js/reader.min.js
OgcBiaozhunguifan/js/reader.min.map
OgcBiaozhunguifan/js/hooks/__init__.py
OgcBiaozhunguifan/js/hooks/extensions/__init__.py
OgcBiaozhunguifan/js/hooks/extensions/highlight.js
OgcBiaozhunguifan/js/libs/__init__.py
OgcBiaozhunguifan/js/libs/jquery.min.js
OgcBiaozhunguifan/js/libs/localforage.min.js
OgcBiaozhunguifan/js/libs/screenfull.js
OgcBiaozhunguifan/js/libs/screenfull.min.js
OgcBiaozhunguifan/js/libs/zip.min.js
OgcBiaozhunguifan/js/plugins/__init__.py
OgcBiaozhunguifan/js/plugins/hypothesis.js
OgcBiaozhunguifan/js/plugins/search.js
ogc_biaozhunguifan-2024.3.4.0.dist-info/METADATA
ogc_biaozhunguifan-2024.3.4.0.dist-info/WHEEL
ogc_biaozhunguifan-2024.3.4.0.dist-info/entry_points.txt
ogc_biaozhunguifan-2024.3.4.0.dist-info/top_level.txt
ogc_biaozhunguifan-2024.3.4.0.dist-info/RECORD
